apc_hypaship/__init__.py
apc_hypaship/apc_client.py
apc_hypaship/config.py
apc_hypaship/error.py
apc_hypaship/models/__init__.py
apc_hypaship/models/request/__init__.py
apc_hypaship/models/request/address.py
apc_hypaship/models/request/services.py
apc_hypaship/models/request/shipment.py
apc_hypaship/models/response/__init__.py
apc_hypaship/models/response/address.py
apc_hypaship/models/response/common.py
apc_hypaship/models/response/label_track.py
apc_hypaship/models/response/parcelspecs.py
apc_hypaship/models/response/resp.py
apc_hypaship/models/response/service.py
apc_hypaship/models/response/shipment.py
apc_hypaship-0.1.9.dist-info/WHEEL
apc_hypaship-0.1.9.dist-info/METADATA
apc_hypaship-0.1.9.dist-info/RECORD
