Metadata-Version: 2.3
Name: apc-hypaship
Version: 0.1.9
Summary: Basic API client for APC-Hypaship platform
Author: paw
Author-email: paw <pawrequest@users.noreply.github.com>
Requires-Dist: dotenv>=0.9.9
Requires-Dist: httpx>=0.28.1
Requires-Dist: loguru>=0.7.3
Requires-Dist: pydantic-settings>=2.11.0
Requires-Python: >=3.13
